{
  "output_dir": "/data/yxdeng993/output/PICNet/self_supervised_2d",
  "model": {
    "name": "picnet2d",
    "in_channels": 1,
    "out_channels": 1,
    "final_activation": "sigmoid",
    "zernike_modes": 13,
    "zernike_indices": [3, 4, 5, 6, 7, 8, 9, 10, 11, 12, 13, 14, 15]
  },
  "optics": {
    "pixel_size": 0.300,
    "na": 1.05,
    "lambda_emission": 1.000,
    "lambda_excitation": 0.808,
    "mode": "widefield",
    "zernike_indices": [3, 4, 5, 6, 7, 8, 9, 10, 11, 12, 13, 14, 15]
  },
  "data": {
    "root": "/data/yxdeng993/data/2Dsim",
    "patch_size": [512, 512],
    "train": {
      "image_dir": "abe",
      "object_dir": "OBJ",
      "augment": true,
      "samples_per_epoch": 2000,
      "object_samples_per_epoch": 2000
    },
    "val": {
      "image_dir": "validation/abe",
      "samples_per_epoch": 400
    },
    "test": {
      "image_dir": "Test/abe",
      "samples_per_epoch": 400
    }
  },
  "training": {
    "epochs": 100,
    "batch_size": 16,
    "num_workers": 4,
    "optimizer": "Adam",
    "initial_lr_G": 0.0002,
    "initial_lr_D": 0.00001,
    "lr_scheduler": "StepLR",
    "step_size": 50,
    "gamma": 0.5,
    "min_lr": 0.000004,
    "weight_decay": 0.0,
    "adversarial_weight": 0.001,
    "tv_weight": 0.00001,
    "coeff_l2": 0.0001
  }
}
